.DS_Store
desgld/__init__.py
desgld/desgld_alg.py
desgld/evaluation.py
desgld/network.py
desgld/test.py
desgld-0.1.6.dist-info/LICENSE
desgld-0.1.6.dist-info/METADATA
desgld-0.1.6.dist-info/WHEEL
desgld-0.1.6.dist-info/top_level.txt
desgld-0.1.6.dist-info/RECORD
