Metadata-Version: 2.1
Name: desgld
Version: 0.1.6
Summary: Decentralized stochastic gradient Langevin diffusion
Home-page: https://github.com/mrislambd/desgld_package.git
Author: Rafiq Islam
License-File: LICENSE
Requires-Dist: numpy
Requires-Dist: scipy
Requires-Dist: scikit-learn
Requires-Dist: matplotlib
Requires-Dist: tqdm
Provides-Extra: dev
Requires-Dist: black ; extra == 'dev'
Requires-Dist: isort ; extra == 'dev'
Requires-Dist: flake8 ; extra == 'dev'
Requires-Dist: pre-commit ; extra == 'dev'
